{
  "p1_mpr_target": 0.8,
  "p2_mpr_target": 1.2,
  "p1_mpr_empirical": 0.8,
  "p2_mpr_empirical": 1.2,
  "p1_bull_mult": 0.75,
  "p2_bull_mult": 0.25,
  "is_equal_skill": false,
  "games_per_matchup": 20000,
  "total_matchups": 484,
  "avg_turns": 66.3,
  "avg_darts": 198.0,
  "strategies": [
    "S1",
    "S2",
    "S3",
    "S4",
    "S5",
    "S6",
    "S7",
    "S8",
    "S9",
    "S10",
    "S11",
    "S12",
    "S13",
    "S14",
    "S15",
    "S16",
    "S17",
    "E1",
    "E2",
    "E3",
    "E4",
    "PS"
  ],
  "matrix": [
    [
      18.3,
      16.5,
      16.7,
      17.7,
      17.7,
      15.3,
      15.6,
      15.7,
      15.4,
      16.9,
      17.0,
      17.1,
      16.9,
      17.4,
      17.8,
      17.3,
      17.4,
      17.2,
      16.4,
      15.9,
      16.7,
      17.1
    ],
    [
      18.2,
      14.4,
      14.5,
      14.6,
      14.4,
      12.5,
      11.8,
      11.1,
      9.8,
      16.6,
      15.9,
      16.7,
      16.9,
      16.9,
      16.2,
      16.6,
      16.7,
      19.7,
      14.8,
      14.6,
      14.7,
      14.7
    ],
    [
      17.0,
      13.0,
      13.2,
      14.0,
      13.6,
      9.0,
      9.2,
      8.2,
      7.7,
      14.8,
      15.3,
      15.4,
      15.4,
      15.2,
      15.3,
      15.8,
      15.2,
      18.2,
      12.8,
      13.0,
      12.9,
      13.0
    ],
    [
      16.6,
      12.0,
      12.9,
      13.1,
      13.7,
      6.9,
      7.4,
      7.3,
      7.1,
      14.2,
      14.2,
      14.5,
      14.3,
      14.7,
      14.9,
      14.8,
      14.7,
      15.7,
      12.1,
      12.4,
      12.8,
      12.6
    ],
    [
      16.5,
      12.1,
      13.0,
      13.4,
      14.1,
      6.2,
      6.6,
      6.9,
      7.1,
      14.4,
      14.3,
      13.9,
      14.6,
      14.2,
      14.1,
      14.0,
      14.5,
      13.4,
      12.1,
      12.1,
      12.6,
      12.7
    ],
    [
      16.5,
      9.3,
      9.3,
      8.1,
      6.9,
      6.9,
      5.9,
      4.7,
      4.1,
      13.6,
      13.3,
      13.4,
      13.7,
      13.6,
      13.2,
      14.0,
      13.5,
      17.2,
      9.9,
      9.7,
      9.2,
      7.7
    ],
    [
      16.9,
      7.5,
      7.8,
      7.4,
      6.6,
      4.7,
      4.0,
      3.4,
      3.4,
      13.6,
      13.3,
      13.5,
      13.7,
      13.4,
      13.6,
      13.8,
      13.6,
      16.2,
      7.8,
      8.2,
      7.4,
      7.0
    ],
    [
      16.7,
      6.7,
      7.0,
      7.4,
      6.7,
      3.5,
      3.2,
      3.2,
      3.2,
      13.6,
      13.7,
      13.6,
      13.5,
      13.7,
      13.4,
      13.7,
      13.9,
      12.4,
      7.0,
      7.1,
      7.0,
      7.1
    ],
    [
      16.2,
      6.6,
      6.8,
      7.4,
      7.3,
      2.9,
      3.0,
      3.2,
      3.1,
      14.2,
      13.6,
      13.6,
      13.4,
      13.6,
      13.7,
      13.5,
      13.4,
      9.1,
      6.3,
      6.5,
      6.7,
      6.9
    ],
    [
      17.8,
      16.2,
      16.8,
      16.3,
      17.4,
      16.4,
      16.2,
      15.8,
      15.9,
      17.1,
      16.4,
      17.3,
      16.8,
      16.9,
      16.7,
      16.5,
      17.0,
      16.9,
      16.7,
      17.4,
      16.7,
      17.1
    ],
    [
      17.4,
      14.9,
      15.2,
      15.3,
      16.1,
      14.6,
      14.4,
      14.7,
      14.5,
      14.7,
      15.6,
      15.4,
      15.9,
      15.9,
      15.9,
      15.4,
      15.9,
      15.6,
      15.3,
      15.5,
      15.4,
      15.5
    ],
    [
      16.8,
      14.5,
      14.7,
      14.4,
      15.1,
      13.8,
      13.7,
      13.5,
      13.9,
      14.8,
      14.8,
      14.5,
      15.2,
      14.4,
      14.5,
      14.7,
      14.7,
      14.8,
      14.7,
      14.4,
      14.5,
      14.7
    ],
    [
      16.3,
      14.0,
      13.9,
      14.1,
      14.7,
      13.3,
      13.6,
      13.0,
      13.7,
      14.4,
      14.4,
      14.0,
      13.9,
      14.2,
      14.4,
      14.2,
      14.8,
      15.0,
      14.1,
      13.6,
      14.1,
      14.5
    ],
    [
      16.4,
      14.7,
      14.8,
      14.8,
      14.7,
      14.6,
      14.0,
      14.2,
      14.1,
      14.7,
      15.0,
      14.9,
      15.1,
      15.4,
      15.0,
      15.0,
      15.2,
      15.5,
      14.8,
      14.5,
      15.0,
      15.0
    ],
    [
      16.4,
      14.0,
      14.2,
      14.6,
      14.5,
      13.5,
      13.7,
      13.9,
      13.4,
      14.1,
      14.6,
      14.5,
      14.8,
      14.9,
      14.9,
      14.8,
      14.6,
      14.9,
      14.4,
      14.4,
      14.3,
      14.8
    ],
    [
      16.5,
      13.9,
      13.5,
      14.2,
      14.4,
      13.8,
      13.8,
      13.5,
      13.4,
      14.0,
      14.1,
      14.2,
      14.3,
      14.3,
      14.5,
      14.5,
      14.2,
      14.4,
      14.0,
      14.2,
      14.0,
      14.1
    ],
    [
      16.6,
      14.4,
      13.9,
      14.2,
      14.2,
      13.3,
      13.0,
      13.3,
      13.7,
      13.5,
      13.8,
      14.0,
      13.9,
      14.1,
      14.6,
      14.2,
      14.2,
      14.7,
      14.0,
      13.8,
      13.8,
      14.2
    ],
    [
      18.3,
      11.5,
      9.8,
      8.7,
      7.7,
      7.9,
      6.3,
      5.1,
      4.7,
      17.8,
      17.5,
      16.8,
      17.2,
      17.4,
      16.9,
      17.1,
      16.7,
      16.0,
      11.1,
      11.2,
      10.9,
      11.1
    ],
    [
      18.6,
      14.4,
      14.9,
      14.8,
      14.1,
      11.9,
      12.0,
      10.6,
      9.5,
      16.4,
      16.5,
      16.5,
      17.1,
      17.0,
      16.7,
      16.8,
      17.1,
      19.9,
      14.7,
      14.9,
      14.6,
      14.4
    ],
    [
      18.0,
      13.7,
      14.3,
      14.0,
      13.2,
      11.8,
      11.6,
      10.1,
      9.0,
      15.8,
      15.9,
      15.7,
      15.7,
      15.6,
      16.2,
      16.3,
      15.9,
      19.3,
      14.2,
      14.4,
      13.6,
      13.3
    ],
    [
      17.2,
      14.0,
      13.6,
      14.3,
      13.4,
      11.1,
      11.0,
      10.1,
      9.3,
      15.7,
      15.8,
      15.7,
      15.9,
      15.9,
      15.8,
      15.9,
      15.5,
      19.4,
      13.6,
      14.3,
      14.0,
      14.3
    ],
    [
      15.7,
      13.1,
      13.5,
      13.2,
      14.1,
      8.4,
      9.3,
      8.8,
      8.5,
      14.3,
      14.3,
      14.4,
      14.6,
      14.7,
      13.9,
      14.7,
      14.7,
      19.4,
      12.8,
      13.2,
      13.2,
      14.4
    ]
  ],
  "averages_p1": {
    "S1": 16.8,
    "S2": 15.1,
    "S3": 13.5,
    "S4": 12.7,
    "S5": 12.4,
    "S6": 10.6,
    "S7": 9.9,
    "S8": 9.4,
    "S9": 9.1,
    "S10": 16.7,
    "S11": 15.4,
    "S12": 14.6,
    "S13": 14.2,
    "S14": 14.9,
    "S15": 14.5,
    "S16": 14.2,
    "S17": 14.1,
    "E1": 12.6,
    "E2": 15.2,
    "E3": 14.4,
    "E4": 14.4,
    "PS": 13.3
  },
  "averages_p2": {
    "S1": 83.0,
    "S2": 87.2,
    "S3": 87.1,
    "S4": 87.0,
    "S5": 87.1,
    "S6": 89.4,
    "S7": 89.6,
    "S8": 90.0,
    "S9": 90.2,
    "S10": 85.0,
    "S11": 85.0,
    "S12": 85.0,
    "S13": 84.9,
    "S14": 84.8,
    "S15": 84.9,
    "S16": 84.8,
    "S17": 84.8,
    "E1": 83.9,
    "E2": 87.1,
    "E3": 87.0,
    "E4": 87.1,
    "PS": 87.0
  },
  "rankings_p1": [
    {
      "name": "S1",
      "avg": 16.8
    },
    {
      "name": "S10",
      "avg": 16.7
    },
    {
      "name": "S11",
      "avg": 15.4
    },
    {
      "name": "E2",
      "avg": 15.2
    },
    {
      "name": "S2",
      "avg": 15.1
    },
    {
      "name": "S14",
      "avg": 14.9
    },
    {
      "name": "S12",
      "avg": 14.6
    },
    {
      "name": "S15",
      "avg": 14.5
    },
    {
      "name": "E3",
      "avg": 14.4
    },
    {
      "name": "E4",
      "avg": 14.4
    },
    {
      "name": "S13",
      "avg": 14.2
    },
    {
      "name": "S16",
      "avg": 14.2
    },
    {
      "name": "S17",
      "avg": 14.1
    },
    {
      "name": "S3",
      "avg": 13.5
    },
    {
      "name": "PS",
      "avg": 13.3
    },
    {
      "name": "S4",
      "avg": 12.7
    },
    {
      "name": "E1",
      "avg": 12.6
    },
    {
      "name": "S5",
      "avg": 12.4
    },
    {
      "name": "S6",
      "avg": 10.6
    },
    {
      "name": "S7",
      "avg": 9.9
    },
    {
      "name": "S8",
      "avg": 9.4
    },
    {
      "name": "S9",
      "avg": 9.1
    }
  ],
  "rankings_p2": [
    {
      "name": "S9",
      "avg": 90.2
    },
    {
      "name": "S8",
      "avg": 90.0
    },
    {
      "name": "S7",
      "avg": 89.6
    },
    {
      "name": "S6",
      "avg": 89.4
    },
    {
      "name": "S2",
      "avg": 87.2
    },
    {
      "name": "S3",
      "avg": 87.1
    },
    {
      "name": "S5",
      "avg": 87.1
    },
    {
      "name": "E2",
      "avg": 87.1
    },
    {
      "name": "E4",
      "avg": 87.1
    },
    {
      "name": "S4",
      "avg": 87.0
    },
    {
      "name": "E3",
      "avg": 87.0
    },
    {
      "name": "PS",
      "avg": 87.0
    },
    {
      "name": "S10",
      "avg": 85.0
    },
    {
      "name": "S11",
      "avg": 85.0
    },
    {
      "name": "S12",
      "avg": 85.0
    },
    {
      "name": "S13",
      "avg": 84.9
    },
    {
      "name": "S15",
      "avg": 84.9
    },
    {
      "name": "S14",
      "avg": 84.8
    },
    {
      "name": "S16",
      "avg": 84.8
    },
    {
      "name": "S17",
      "avg": 84.8
    },
    {
      "name": "E1",
      "avg": 83.9
    },
    {
      "name": "S1",
      "avg": 83.0
    }
  ],
  "elapsed_seconds": 1752.6
}