{
  "p1_mpr_target": 3.6,
  "p2_mpr_target": 4.0,
  "p1_mpr_empirical": 3.6,
  "p2_mpr_empirical": 4.0,
  "p1_bull_mult": 0.25,
  "p2_bull_mult": 0.75,
  "is_equal_skill": false,
  "games_per_matchup": 20000,
  "total_matchups": 484,
  "avg_turns": 21.2,
  "avg_darts": 62.7,
  "strategies": [
    "S1",
    "S2",
    "S3",
    "S4",
    "S5",
    "S6",
    "S7",
    "S8",
    "S9",
    "S10",
    "S11",
    "S12",
    "S13",
    "S14",
    "S15",
    "S16",
    "S17",
    "E1",
    "E2",
    "E3",
    "E4",
    "PS"
  ],
  "matrix": [
    [
      28.5,
      27.2,
      28.1,
      28.5,
      28.1,
      25.2,
      26.9,
      26.1,
      26.8,
      28.2,
      28.8,
      28.2,
      28.5,
      28.4,
      28.7,
      28.9,
      28.5,
      25.4,
      26.6,
      27.1,
      27.5,
      28.9
    ],
    [
      31.4,
      26.1,
      26.5,
      27.0,
      26.5,
      24.0,
      26.3,
      26.3,
      25.4,
      28.2,
      29.2,
      29.4,
      28.9,
      29.8,
      29.7,
      29.6,
      29.3,
      31.0,
      25.9,
      27.2,
      26.2,
      24.7
    ],
    [
      29.1,
      22.8,
      24.9,
      25.0,
      24.8,
      21.4,
      23.9,
      23.7,
      22.2,
      27.4,
      28.6,
      28.9,
      28.1,
      28.2,
      28.1,
      28.5,
      28.3,
      27.1,
      21.9,
      22.7,
      23.0,
      23.5
    ],
    [
      27.0,
      23.4,
      25.0,
      25.0,
      24.5,
      22.5,
      23.9,
      23.1,
      21.9,
      26.0,
      26.6,
      27.0,
      27.8,
      27.0,
      27.8,
      27.5,
      27.0,
      24.7,
      22.4,
      23.6,
      24.3,
      24.0
    ],
    [
      26.9,
      24.0,
      25.7,
      25.8,
      25.4,
      23.3,
      23.2,
      23.0,
      21.4,
      25.8,
      27.1,
      26.7,
      27.1,
      27.2,
      26.2,
      27.5,
      27.5,
      24.1,
      23.5,
      25.4,
      25.3,
      24.7
    ],
    [
      29.4,
      19.1,
      21.2,
      21.4,
      21.5,
      19.8,
      22.6,
      22.9,
      21.7,
      24.8,
      25.4,
      26.6,
      25.9,
      25.6,
      25.8,
      26.0,
      26.3,
      30.5,
      19.0,
      19.3,
      18.4,
      16.0
    ],
    [
      28.2,
      17.9,
      20.7,
      21.4,
      20.9,
      19.6,
      21.9,
      22.1,
      19.5,
      26.4,
      26.9,
      27.2,
      26.7,
      26.4,
      27.0,
      27.4,
      27.3,
      29.5,
      17.2,
      18.2,
      18.4,
      16.2
    ],
    [
      27.8,
      19.9,
      22.9,
      22.8,
      22.0,
      21.5,
      22.5,
      20.7,
      19.5,
      26.6,
      27.2,
      27.7,
      27.5,
      27.3,
      27.2,
      27.3,
      27.1,
      29.8,
      19.6,
      21.6,
      21.6,
      18.8
    ],
    [
      28.3,
      22.1,
      25.1,
      24.8,
      23.5,
      22.4,
      23.1,
      20.9,
      19.7,
      26.8,
      26.8,
      27.2,
      27.6,
      26.8,
      27.3,
      26.9,
      27.9,
      29.2,
      22.1,
      24.4,
      23.2,
      20.9
    ],
    [
      29.2,
      28.4,
      29.4,
      30.2,
      29.9,
      29.3,
      28.2,
      28.8,
      28.9,
      28.2,
      30.0,
      29.8,
      29.6,
      29.5,
      29.4,
      29.9,
      29.7,
      25.5,
      28.8,
      29.2,
      29.7,
      30.5
    ],
    [
      27.5,
      26.8,
      27.0,
      27.5,
      28.1,
      27.6,
      26.9,
      27.1,
      27.7,
      27.3,
      27.8,
      28.1,
      28.2,
      27.9,
      27.9,
      28.0,
      28.2,
      24.8,
      26.9,
      27.9,
      27.9,
      28.1
    ],
    [
      26.8,
      26.2,
      26.6,
      27.3,
      26.9,
      26.6,
      26.5,
      27.0,
      26.8,
      26.0,
      27.5,
      27.2,
      26.9,
      27.0,
      26.8,
      27.0,
      26.9,
      25.0,
      25.8,
      27.2,
      26.3,
      27.8
    ],
    [
      26.9,
      26.5,
      26.7,
      27.1,
      27.1,
      26.4,
      26.8,
      26.1,
      26.7,
      26.0,
      26.7,
      27.3,
      27.0,
      26.4,
      26.7,
      26.8,
      27.5,
      24.4,
      25.6,
      26.5,
      26.4,
      27.2
    ],
    [
      27.2,
      26.5,
      27.3,
      27.2,
      28.0,
      26.3,
      26.3,
      26.7,
      27.0,
      26.3,
      27.2,
      27.3,
      27.5,
      26.9,
      27.2,
      27.8,
      27.1,
      24.9,
      26.1,
      27.4,
      27.1,
      27.3
    ],
    [
      26.8,
      25.8,
      26.4,
      27.1,
      26.9,
      26.6,
      26.3,
      25.8,
      26.0,
      25.9,
      26.4,
      26.4,
      26.8,
      26.6,
      26.3,
      26.5,
      27.2,
      24.8,
      26.5,
      27.0,
      26.4,
      27.2
    ],
    [
      26.6,
      25.7,
      26.7,
      27.0,
      27.2,
      27.0,
      26.3,
      26.2,
      26.3,
      25.5,
      26.8,
      27.1,
      27.1,
      27.0,
      27.2,
      27.2,
      26.6,
      24.2,
      25.9,
      27.7,
      26.3,
      27.7
    ],
    [
      26.8,
      25.7,
      26.3,
      26.5,
      27.1,
      26.1,
      25.8,
      26.4,
      26.3,
      25.9,
      26.3,
      27.0,
      26.7,
      25.9,
      26.3,
      27.2,
      27.0,
      25.0,
      25.7,
      26.5,
      25.8,
      26.9
    ],
    [
      28.5,
      16.2,
      11.3,
      10.8,
      10.1,
      10.3,
      9.1,
      9.6,
      9.7,
      27.9,
      26.5,
      26.9,
      27.7,
      27.2,
      27.3,
      27.4,
      27.0,
      25.2,
      16.1,
      16.1,
      14.8,
      15.3
    ],
    [
      31.2,
      26.2,
      26.6,
      27.3,
      26.6,
      23.9,
      25.5,
      26.2,
      25.0,
      28.6,
      29.3,
      29.3,
      29.4,
      29.1,
      29.3,
      29.5,
      29.5,
      30.6,
      26.7,
      27.3,
      26.2,
      25.3
    ],
    [
      28.8,
      22.1,
      21.4,
      21.6,
      21.3,
      21.3,
      23.2,
      22.8,
      21.7,
      25.8,
      25.9,
      26.5,
      27.4,
      26.1,
      26.6,
      26.7,
      26.5,
      28.9,
      22.9,
      23.5,
      21.6,
      19.6
    ],
    [
      29.3,
      24.9,
      25.5,
      25.8,
      24.7,
      23.5,
      25.4,
      25.0,
      23.9,
      27.6,
      28.2,
      28.3,
      28.3,
      28.6,
      28.7,
      28.5,
      28.7,
      30.1,
      24.5,
      26.3,
      25.0,
      24.5
    ],
    [
      27.5,
      26.6,
      26.5,
      24.9,
      24.8,
      27.2,
      26.3,
      24.3,
      22.9,
      26.3,
      26.3,
      26.4,
      26.1,
      26.7,
      26.9,
      26.8,
      26.3,
      34.1,
      26.3,
      28.4,
      26.9,
      26.1
    ]
  ],
  "averages_p1": {
    "S1": 27.7,
    "S2": 27.7,
    "S3": 25.6,
    "S4": 25.1,
    "S5": 25.3,
    "S6": 23.1,
    "S7": 23.0,
    "S8": 24.0,
    "S9": 24.9,
    "S10": 29.2,
    "S11": 27.5,
    "S12": 26.7,
    "S13": 26.6,
    "S14": 26.9,
    "S15": 26.4,
    "S16": 26.6,
    "S17": 26.3,
    "E1": 19.1,
    "E2": 27.7,
    "E3": 24.2,
    "E4": 26.6,
    "PS": 26.6
  },
  "averages_p2": {
    "S1": 71.8,
    "S2": 75.9,
    "S3": 75.1,
    "S4": 74.9,
    "S5": 75.2,
    "S6": 76.3,
    "S7": 75.6,
    "S8": 75.9,
    "S9": 76.5,
    "S10": 73.3,
    "S11": 72.7,
    "S12": 72.4,
    "S13": 72.4,
    "S14": 72.7,
    "S15": 72.5,
    "S16": 72.3,
    "S17": 72.4,
    "E1": 72.8,
    "E2": 76.1,
    "E3": 75.0,
    "E4": 75.5,
    "PS": 75.9
  },
  "rankings_p1": [
    {
      "name": "S10",
      "avg": 29.2
    },
    {
      "name": "S1",
      "avg": 27.7
    },
    {
      "name": "S2",
      "avg": 27.7
    },
    {
      "name": "E2",
      "avg": 27.7
    },
    {
      "name": "S11",
      "avg": 27.5
    },
    {
      "name": "S14",
      "avg": 26.9
    },
    {
      "name": "S12",
      "avg": 26.7
    },
    {
      "name": "S13",
      "avg": 26.6
    },
    {
      "name": "S16",
      "avg": 26.6
    },
    {
      "name": "E4",
      "avg": 26.6
    },
    {
      "name": "PS",
      "avg": 26.6
    },
    {
      "name": "S15",
      "avg": 26.4
    },
    {
      "name": "S17",
      "avg": 26.3
    },
    {
      "name": "S3",
      "avg": 25.6
    },
    {
      "name": "S5",
      "avg": 25.3
    },
    {
      "name": "S4",
      "avg": 25.1
    },
    {
      "name": "S9",
      "avg": 24.9
    },
    {
      "name": "E3",
      "avg": 24.2
    },
    {
      "name": "S8",
      "avg": 24.0
    },
    {
      "name": "S6",
      "avg": 23.1
    },
    {
      "name": "S7",
      "avg": 23.0
    },
    {
      "name": "E1",
      "avg": 19.1
    }
  ],
  "rankings_p2": [
    {
      "name": "S9",
      "avg": 76.5
    },
    {
      "name": "S6",
      "avg": 76.3
    },
    {
      "name": "E2",
      "avg": 76.1
    },
    {
      "name": "S2",
      "avg": 75.9
    },
    {
      "name": "S8",
      "avg": 75.9
    },
    {
      "name": "PS",
      "avg": 75.9
    },
    {
      "name": "S7",
      "avg": 75.6
    },
    {
      "name": "E4",
      "avg": 75.5
    },
    {
      "name": "S5",
      "avg": 75.2
    },
    {
      "name": "S3",
      "avg": 75.1
    },
    {
      "name": "E3",
      "avg": 75.0
    },
    {
      "name": "S4",
      "avg": 74.9
    },
    {
      "name": "S10",
      "avg": 73.3
    },
    {
      "name": "E1",
      "avg": 72.8
    },
    {
      "name": "S11",
      "avg": 72.7
    },
    {
      "name": "S14",
      "avg": 72.7
    },
    {
      "name": "S15",
      "avg": 72.5
    },
    {
      "name": "S12",
      "avg": 72.4
    },
    {
      "name": "S13",
      "avg": 72.4
    },
    {
      "name": "S17",
      "avg": 72.4
    },
    {
      "name": "S16",
      "avg": 72.3
    },
    {
      "name": "S1",
      "avg": 71.8
    }
  ],
  "elapsed_seconds": 565.0
}